{
    "input_path": "sample3/license_5_常雪.jpeg",
    "page_index": null,
    "model_settings": {
        "use_doc_preprocessor": true,
        "use_textline_orientation": false
    },
    "doc_preprocessor_res": {
        "input_path": null,
        "page_index": null,
        "model_settings": {
            "use_doc_orientation_classify": false,
            "use_doc_unwarping": false
        },
        "angle": -1
    },
    "dt_polys": [
        [
            [
                29,
                19
            ],
            [
                152,
                19
            ],
            [
                152,
                44
            ],
            [
                29,
                44
            ]
        ],
        [
            [
                301,
                15
            ],
            [
                460,
                12
            ],
            [
                460,
                44
            ],
            [
                301,
                47
            ]
        ],
        [
            [
                536,
                20
            ],
            [
                584,
                20
            ],
            [
                584,
                61
            ],
            [
                536,
                61
            ]
        ],
        [
            [
                29,
                41
            ],
            [
                179,
                41
            ],
            [
                179,
                59
            ],
            [
                29,
                59
            ]
        ],
        [
            [
                317,
                41
            ],
            [
                436,
                40
            ],
            [
                436,
                58
            ],
            [
                317,
                59
            ]
        ],
        [
            [
                29,
                64
            ],
            [
                68,
                64
            ],
            [
                68,
                85
            ],
            [
                29,
                85
            ]
        ],
        [
            [
                75,
                63
            ],
            [
                124,
                63
            ],
            [
                124,
                89
            ],
            [
                75,
                89
            ]
        ],
        [
            [
                27,
                89
            ],
            [
                64,
                89
            ],
            [
                64,
                109
            ],
            [
                27,
                109
            ]
        ],
        [
            [
                76,
                87
            ],
            [
                187,
                87
            ],
            [
                187,
                113
            ],
            [
                76,
                113
            ]
        ],
        [
            [
                26,
                116
            ],
            [
                91,
                116
            ],
            [
                91,
                135
            ],
            [
                26,
                135
            ]
        ],
        [
            [
                117,
                111
            ],
            [
                278,
                111
            ],
            [
                278,
                134
            ],
            [
                117,
                135
            ]
        ],
        [
            [
                285,
                111
            ],
            [
                515,
                109
            ],
            [
                515,
                136
            ],
            [
                285,
                137
            ]
        ],
        [
            [
                25,
                137
            ],
            [
                132,
                137
            ],
            [
                132,
                155
            ],
            [
                25,
                155
            ]
        ],
        [
            [
                173,
                136
            ],
            [
                187,
                136
            ],
            [
                187,
                149
            ],
            [
                173,
                149
            ]
        ],
        [
            [
                222,
                137
            ],
            [
                231,
                137
            ],
            [
                231,
                148
            ],
            [
                222,
                148
            ]
        ],
        [
            [
                268,
                138
            ],
            [
                280,
                138
            ],
            [
                280,
                151
            ],
            [
                268,
                151
            ]
        ],
        [
            [
                287,
                136
            ],
            [
                316,
                138
            ],
            [
                315,
                156
            ],
            [
                285,
                154
            ]
        ],
        [
            [
                374,
                137
            ],
            [
                521,
                135
            ],
            [
                521,
                155
            ],
            [
                375,
                157
            ]
        ],
        [
            [
                23,
                169
            ],
            [
                77,
                169
            ],
            [
                77,
                189
            ],
            [
                23,
                189
            ]
        ],
        [
            [
                98,
                166
            ],
            [
                550,
                161
            ],
            [
                551,
                185
            ],
            [
                98,
                190
            ]
        ],
        [
            [
                23,
                187
            ],
            [
                81,
                185
            ],
            [
                82,
                205
            ],
            [
                23,
                206
            ]
        ],
        [
            [
                22,
                216
            ],
            [
                88,
                216
            ],
            [
                88,
                237
            ],
            [
                22,
                237
            ]
        ],
        [
            [
                99,
                209
            ],
            [
                377,
                212
            ],
            [
                376,
                239
            ],
            [
                99,
                236
            ]
        ],
        [
            [
                19,
                239
            ],
            [
                72,
                239
            ],
            [
                72,
                258
            ],
            [
                19,
                258
            ]
        ],
        [
            [
                86,
                237
            ],
            [
                153,
                238
            ],
            [
                152,
                254
            ],
            [
                86,
                253
            ]
        ],
        [
            [
                87,
                252
            ],
            [
                182,
                252
            ],
            [
                182,
                268
            ],
            [
                87,
                268
            ]
        ],
        [
            [
                337,
                252
            ],
            [
                499,
                252
            ],
            [
                499,
                274
            ],
            [
                337,
                274
            ]
        ],
        [
            [
                87,
                264
            ],
            [
                163,
                266
            ],
            [
                163,
                282
            ],
            [
                86,
                280
            ]
        ],
        [
            [
                193,
                262
            ],
            [
                307,
                262
            ],
            [
                307,
                283
            ],
            [
                193,
                283
            ]
        ],
        [
            [
                87,
                277
            ],
            [
                182,
                279
            ],
            [
                182,
                296
            ],
            [
                87,
                294
            ]
        ],
        [
            [
                337,
                269
            ],
            [
                484,
                272
            ],
            [
                484,
                297
            ],
            [
                336,
                295
            ]
        ],
        [
            [
                23,
                299
            ],
            [
                157,
                299
            ],
            [
                157,
                318
            ],
            [
                23,
                318
            ]
        ],
        [
            [
                186,
                310
            ],
            [
                234,
                310
            ],
            [
                234,
                332
            ],
            [
                186,
                332
            ]
        ],
        [
            [
                232,
                307
            ],
            [
                499,
                309
            ],
            [
                499,
                334
            ],
            [
                232,
                332
            ]
        ],
        [
            [
                21,
                318
            ],
            [
                134,
                318
            ],
            [
                134,
                334
            ],
            [
                21,
                334
            ]
        ],
        [
            [
                22,
                334
            ],
            [
                181,
                334
            ],
            [
                181,
                354
            ],
            [
                22,
                354
            ]
        ],
        [
            [
                211,
                334
            ],
            [
                225,
                334
            ],
            [
                225,
                348
            ],
            [
                211,
                348
            ]
        ],
        [
            [
                470,
                334
            ],
            [
                486,
                334
            ],
            [
                486,
                350
            ],
            [
                470,
                350
            ]
        ],
        [
            [
                18,
                362
            ],
            [
                105,
                359
            ],
            [
                105,
                380
            ],
            [
                18,
                382
            ]
        ],
        [
            [
                112,
                358
            ],
            [
                417,
                358
            ],
            [
                417,
                379
            ],
            [
                112,
                379
            ]
        ],
        [
            [
                439,
                356
            ],
            [
                516,
                356
            ],
            [
                516,
                382
            ],
            [
                439,
                382
            ]
        ],
        [
            [
                710,
                371
            ],
            [
                757,
                371
            ],
            [
                757,
                388
            ],
            [
                710,
                388
            ]
        ],
        [
            [
                17,
                390
            ],
            [
                527,
                390
            ],
            [
                527,
                412
            ],
            [
                17,
                412
            ]
        ],
        [
            [
                715,
                411
            ],
            [
                767,
                414
            ],
            [
                766,
                435
            ],
            [
                714,
                433
            ]
        ],
        [
            [
                16,
                429
            ],
            [
                120,
                429
            ],
            [
                120,
                450
            ],
            [
                16,
                450
            ]
        ],
        [
            [
                144,
                422
            ],
            [
                494,
                424
            ],
            [
                494,
                452
            ],
            [
                144,
                449
            ]
        ],
        [
            [
                510,
                428
            ],
            [
                551,
                428
            ],
            [
                551,
                448
            ],
            [
                510,
                448
            ]
        ],
        [
            [
                577,
                427
            ],
            [
                716,
                428
            ],
            [
                716,
                449
            ],
            [
                577,
                448
            ]
        ],
        [
            [
                723,
                432
            ],
            [
                759,
                432
            ],
            [
                759,
                447
            ],
            [
                723,
                447
            ]
        ],
        [
            [
                194,
                450
            ],
            [
                425,
                450
            ],
            [
                425,
                466
            ],
            [
                194,
                466
            ]
        ],
        [
            [
                732,
                444
            ],
            [
                763,
                447
            ],
            [
                762,
                460
            ],
            [
                731,
                457
            ]
        ]
    ],
    "text_det_params": {
        "limit_side_len": 736,
        "limit_type": "min",
        "thresh": 0.3,
        "max_side_limit": 4000,
        "box_thresh": 0.6,
        "unclip_ratio": 1.5
    },
    "text_type": "general",
    "textline_orientation_angles": [
        -1,
        -1,
        -1,
        -1,
        -1,
        -1,
        -1,
        -1,
        -1,
        -1,
        -1,
        -1,
        -1,
        -1,
        -1,
        -1,
        -1,
        -1,
        -1,
        -1,
        -1,
        -1,
        -1,
        -1,
        -1,
        -1,
        -1,
        -1,
        -1,
        -1,
        -1,
        -1,
        -1,
        -1,
        -1,
        -1,
        -1,
        -1,
        -1,
        -1,
        -1,
        -1,
        -1,
        -1,
        -1,
        -1,
        -1,
        -1,
        -1,
        -1,
        -1
    ],
    "text_rec_score_thresh": 0.0,
    "rec_texts": [
        "日本国政府",
        "在留力ード",
        "番号",
        "GOVERNVENT OF JAPAN",
        "RESIDENCE CARD",
        "氏名",
        "常雪",
        "NAME",
        "Chang Xue",
        "生年月日",
        "2020年9月23日",
        "生别女F.国籍·地城中国",
        "DATE OF BIRTH",
        "Y",
        "H",
        "D",
        "SEX",
        "NATIONALITY/REGION",
        "住居地",
        "兵庫県北九州市西新宿28-17横浜市八イラズ1906号室",
        "ADDRESS",
        "在留资格",
        "技術·人文知識·国際業務",
        "STATUS",
        "Engineer/",
        "Specialist in",
        "在留資格に基く",
        "Humanities/",
        "就労制限の有無",
        "Int Iservices",
        "就労活動のみ可",
        "在留期間（满了日）",
        "5年",
        "（2026年92日16日）",
        "PERIOD OF STAY",
        "(DATE OF EXPIRATION)",
        "Y",
        "D",
        "許可の種類",
        "在留期間更新許可（東京出入国在留管理局長）",
        "MOJ",
        "MOJ",
        "許可年月日2021年03月16日交付年月日2021年03月16日",
        "出天的理",
        "二のカ一ドは",
        "2026年03月16日まで有効",
        "です",
        "出入国应留管理方長富",
        "登",
        "PERIOD OF VALIDITY OF THIS CARD",
        ""
    ],
    "rec_scores": [
        0.9904994964599609,
        0.8672884106636047,
        0.9772418737411499,
        0.8188539743423462,
        0.9144296646118164,
        0.9545657634735107,
        0.9996728301048279,
        0.8925179839134216,
        0.9718543291091919,
        0.9790502786636353,
        0.9986655116081238,
        0.915256917476654,
        0.932897686958313,
        0.9773813486099243,
        0.398377388715744,
        0.9893372058868408,
        0.96324223279953,
        0.9927418231964111,
        0.9891610145568848,
        0.9300197958946228,
        0.9978815913200378,
        0.9784721732139587,
        0.9197728633880615,
        0.992682695388794,
        0.9121420383453369,
        0.9624348878860474,
        0.9160706400871277,
        0.9344400763511658,
        0.9431300759315491,
        0.8599376678466797,
        0.9547033905982971,
        0.8691623210906982,
        0.9972668290138245,
        0.9736055135726929,
        0.9234591722488403,
        0.8988558650016785,
        0.9823402166366577,
        0.9484837055206299,
        0.8890537023544312,
        0.9255353212356567,
        0.8958735466003418,
        0.94675612449646,
        0.9975470900535583,
        0.5975040197372437,
        0.7311980128288269,
        0.9531809687614441,
        0.9753382205963135,
        0.7373214960098267,
        0.11766064167022705,
        0.9501062631607056,
        0.0
    ],
    "rec_polys": [
        [
            [
                29,
                19
            ],
            [
                152,
                19
            ],
            [
                152,
                44
            ],
            [
                29,
                44
            ]
        ],
        [
            [
                301,
                15
            ],
            [
                460,
                12
            ],
            [
                460,
                44
            ],
            [
                301,
                47
            ]
        ],
        [
            [
                536,
                20
            ],
            [
                584,
                20
            ],
            [
                584,
                61
            ],
            [
                536,
                61
            ]
        ],
        [
            [
                29,
                41
            ],
            [
                179,
                41
            ],
            [
                179,
                59
            ],
            [
                29,
                59
            ]
        ],
        [
            [
                317,
                41
            ],
            [
                436,
                40
            ],
            [
                436,
                58
            ],
            [
                317,
                59
            ]
        ],
        [
            [
                29,
                64
            ],
            [
                68,
                64
            ],
            [
                68,
                85
            ],
            [
                29,
                85
            ]
        ],
        [
            [
                75,
                63
            ],
            [
                124,
                63
            ],
            [
                124,
                89
            ],
            [
                75,
                89
            ]
        ],
        [
            [
                27,
                89
            ],
            [
                64,
                89
            ],
            [
                64,
                109
            ],
            [
                27,
                109
            ]
        ],
        [
            [
                76,
                87
            ],
            [
                187,
                87
            ],
            [
                187,
                113
            ],
            [
                76,
                113
            ]
        ],
        [
            [
                26,
                116
            ],
            [
                91,
                116
            ],
            [
                91,
                135
            ],
            [
                26,
                135
            ]
        ],
        [
            [
                117,
                111
            ],
            [
                278,
                111
            ],
            [
                278,
                134
            ],
            [
                117,
                135
            ]
        ],
        [
            [
                285,
                111
            ],
            [
                515,
                109
            ],
            [
                515,
                136
            ],
            [
                285,
                137
            ]
        ],
        [
            [
                25,
                137
            ],
            [
                132,
                137
            ],
            [
                132,
                155
            ],
            [
                25,
                155
            ]
        ],
        [
            [
                173,
                136
            ],
            [
                187,
                136
            ],
            [
                187,
                149
            ],
            [
                173,
                149
            ]
        ],
        [
            [
                222,
                137
            ],
            [
                231,
                137
            ],
            [
                231,
                148
            ],
            [
                222,
                148
            ]
        ],
        [
            [
                268,
                138
            ],
            [
                280,
                138
            ],
            [
                280,
                151
            ],
            [
                268,
                151
            ]
        ],
        [
            [
                287,
                136
            ],
            [
                316,
                138
            ],
            [
                315,
                156
            ],
            [
                285,
                154
            ]
        ],
        [
            [
                374,
                137
            ],
            [
                521,
                135
            ],
            [
                521,
                155
            ],
            [
                375,
                157
            ]
        ],
        [
            [
                23,
                169
            ],
            [
                77,
                169
            ],
            [
                77,
                189
            ],
            [
                23,
                189
            ]
        ],
        [
            [
                98,
                166
            ],
            [
                550,
                161
            ],
            [
                551,
                185
            ],
            [
                98,
                190
            ]
        ],
        [
            [
                23,
                187
            ],
            [
                81,
                185
            ],
            [
                82,
                205
            ],
            [
                23,
                206
            ]
        ],
        [
            [
                22,
                216
            ],
            [
                88,
                216
            ],
            [
                88,
                237
            ],
            [
                22,
                237
            ]
        ],
        [
            [
                99,
                209
            ],
            [
                377,
                212
            ],
            [
                376,
                239
            ],
            [
                99,
                236
            ]
        ],
        [
            [
                19,
                239
            ],
            [
                72,
                239
            ],
            [
                72,
                258
            ],
            [
                19,
                258
            ]
        ],
        [
            [
                86,
                237
            ],
            [
                153,
                238
            ],
            [
                152,
                254
            ],
            [
                86,
                253
            ]
        ],
        [
            [
                87,
                252
            ],
            [
                182,
                252
            ],
            [
                182,
                268
            ],
            [
                87,
                268
            ]
        ],
        [
            [
                337,
                252
            ],
            [
                499,
                252
            ],
            [
                499,
                274
            ],
            [
                337,
                274
            ]
        ],
        [
            [
                87,
                264
            ],
            [
                163,
                266
            ],
            [
                163,
                282
            ],
            [
                86,
                280
            ]
        ],
        [
            [
                193,
                262
            ],
            [
                307,
                262
            ],
            [
                307,
                283
            ],
            [
                193,
                283
            ]
        ],
        [
            [
                87,
                277
            ],
            [
                182,
                279
            ],
            [
                182,
                296
            ],
            [
                87,
                294
            ]
        ],
        [
            [
                337,
                269
            ],
            [
                484,
                272
            ],
            [
                484,
                297
            ],
            [
                336,
                295
            ]
        ],
        [
            [
                23,
                299
            ],
            [
                157,
                299
            ],
            [
                157,
                318
            ],
            [
                23,
                318
            ]
        ],
        [
            [
                186,
                310
            ],
            [
                234,
                310
            ],
            [
                234,
                332
            ],
            [
                186,
                332
            ]
        ],
        [
            [
                232,
                307
            ],
            [
                499,
                309
            ],
            [
                499,
                334
            ],
            [
                232,
                332
            ]
        ],
        [
            [
                21,
                318
            ],
            [
                134,
                318
            ],
            [
                134,
                334
            ],
            [
                21,
                334
            ]
        ],
        [
            [
                22,
                334
            ],
            [
                181,
                334
            ],
            [
                181,
                354
            ],
            [
                22,
                354
            ]
        ],
        [
            [
                211,
                334
            ],
            [
                225,
                334
            ],
            [
                225,
                348
            ],
            [
                211,
                348
            ]
        ],
        [
            [
                470,
                334
            ],
            [
                486,
                334
            ],
            [
                486,
                350
            ],
            [
                470,
                350
            ]
        ],
        [
            [
                18,
                362
            ],
            [
                105,
                359
            ],
            [
                105,
                380
            ],
            [
                18,
                382
            ]
        ],
        [
            [
                112,
                358
            ],
            [
                417,
                358
            ],
            [
                417,
                379
            ],
            [
                112,
                379
            ]
        ],
        [
            [
                439,
                356
            ],
            [
                516,
                356
            ],
            [
                516,
                382
            ],
            [
                439,
                382
            ]
        ],
        [
            [
                710,
                371
            ],
            [
                757,
                371
            ],
            [
                757,
                388
            ],
            [
                710,
                388
            ]
        ],
        [
            [
                17,
                390
            ],
            [
                527,
                390
            ],
            [
                527,
                412
            ],
            [
                17,
                412
            ]
        ],
        [
            [
                715,
                411
            ],
            [
                767,
                414
            ],
            [
                766,
                435
            ],
            [
                714,
                433
            ]
        ],
        [
            [
                16,
                429
            ],
            [
                120,
                429
            ],
            [
                120,
                450
            ],
            [
                16,
                450
            ]
        ],
        [
            [
                144,
                422
            ],
            [
                494,
                424
            ],
            [
                494,
                452
            ],
            [
                144,
                449
            ]
        ],
        [
            [
                510,
                428
            ],
            [
                551,
                428
            ],
            [
                551,
                448
            ],
            [
                510,
                448
            ]
        ],
        [
            [
                577,
                427
            ],
            [
                716,
                428
            ],
            [
                716,
                449
            ],
            [
                577,
                448
            ]
        ],
        [
            [
                723,
                432
            ],
            [
                759,
                432
            ],
            [
                759,
                447
            ],
            [
                723,
                447
            ]
        ],
        [
            [
                194,
                450
            ],
            [
                425,
                450
            ],
            [
                425,
                466
            ],
            [
                194,
                466
            ]
        ],
        [
            [
                732,
                444
            ],
            [
                763,
                447
            ],
            [
                762,
                460
            ],
            [
                731,
                457
            ]
        ]
    ],
    "rec_boxes": [
        [
            29,
            19,
            152,
            44
        ],
        [
            301,
            12,
            460,
            47
        ],
        [
            536,
            20,
            584,
            61
        ],
        [
            29,
            41,
            179,
            59
        ],
        [
            317,
            40,
            436,
            59
        ],
        [
            29,
            64,
            68,
            85
        ],
        [
            75,
            63,
            124,
            89
        ],
        [
            27,
            89,
            64,
            109
        ],
        [
            76,
            87,
            187,
            113
        ],
        [
            26,
            116,
            91,
            135
        ],
        [
            117,
            111,
            278,
            135
        ],
        [
            285,
            109,
            515,
            137
        ],
        [
            25,
            137,
            132,
            155
        ],
        [
            173,
            136,
            187,
            149
        ],
        [
            222,
            137,
            231,
            148
        ],
        [
            268,
            138,
            280,
            151
        ],
        [
            285,
            136,
            316,
            156
        ],
        [
            374,
            135,
            521,
            157
        ],
        [
            23,
            169,
            77,
            189
        ],
        [
            98,
            161,
            551,
            190
        ],
        [
            23,
            185,
            82,
            206
        ],
        [
            22,
            216,
            88,
            237
        ],
        [
            99,
            209,
            377,
            239
        ],
        [
            19,
            239,
            72,
            258
        ],
        [
            86,
            237,
            153,
            254
        ],
        [
            87,
            252,
            182,
            268
        ],
        [
            337,
            252,
            499,
            274
        ],
        [
            86,
            264,
            163,
            282
        ],
        [
            193,
            262,
            307,
            283
        ],
        [
            87,
            277,
            182,
            296
        ],
        [
            336,
            269,
            484,
            297
        ],
        [
            23,
            299,
            157,
            318
        ],
        [
            186,
            310,
            234,
            332
        ],
        [
            232,
            307,
            499,
            334
        ],
        [
            21,
            318,
            134,
            334
        ],
        [
            22,
            334,
            181,
            354
        ],
        [
            211,
            334,
            225,
            348
        ],
        [
            470,
            334,
            486,
            350
        ],
        [
            18,
            359,
            105,
            382
        ],
        [
            112,
            358,
            417,
            379
        ],
        [
            439,
            356,
            516,
            382
        ],
        [
            710,
            371,
            757,
            388
        ],
        [
            17,
            390,
            527,
            412
        ],
        [
            714,
            411,
            767,
            435
        ],
        [
            16,
            429,
            120,
            450
        ],
        [
            144,
            422,
            494,
            452
        ],
        [
            510,
            428,
            551,
            448
        ],
        [
            577,
            427,
            716,
            449
        ],
        [
            723,
            432,
            759,
            447
        ],
        [
            194,
            450,
            425,
            466
        ],
        [
            731,
            444,
            763,
            460
        ]
    ]
}