{
    "input_path": "sample3/license_58_方雅.jpeg",
    "page_index": null,
    "model_settings": {
        "use_doc_preprocessor": true,
        "use_textline_orientation": false
    },
    "doc_preprocessor_res": {
        "input_path": null,
        "page_index": null,
        "model_settings": {
            "use_doc_orientation_classify": false,
            "use_doc_unwarping": false
        },
        "angle": -1
    },
    "dt_polys": [
        [
            [
                32,
                15
            ],
            [
                155,
                15
            ],
            [
                155,
                39
            ],
            [
                32,
                39
            ]
        ],
        [
            [
                304,
                14
            ],
            [
                462,
                13
            ],
            [
                462,
                45
            ],
            [
                304,
                46
            ]
        ],
        [
            [
                541,
                24
            ],
            [
                584,
                24
            ],
            [
                584,
                53
            ],
            [
                541,
                53
            ]
        ],
        [
            [
                31,
                37
            ],
            [
                183,
                37
            ],
            [
                183,
                57
            ],
            [
                31,
                57
            ]
        ],
        [
            [
                319,
                41
            ],
            [
                438,
                41
            ],
            [
                438,
                59
            ],
            [
                319,
                59
            ]
        ],
        [
            [
                563,
                46
            ],
            [
                577,
                46
            ],
            [
                577,
                55
            ],
            [
                563,
                55
            ]
        ],
        [
            [
                31,
                59
            ],
            [
                80,
                59
            ],
            [
                80,
                81
            ],
            [
                31,
                81
            ]
        ],
        [
            [
                75,
                59
            ],
            [
                127,
                59
            ],
            [
                127,
                87
            ],
            [
                75,
                87
            ]
        ],
        [
            [
                29,
                84
            ],
            [
                66,
                84
            ],
            [
                66,
                104
            ],
            [
                29,
                104
            ]
        ],
        [
            [
                77,
                83
            ],
            [
                159,
                83
            ],
            [
                159,
                110
            ],
            [
                77,
                110
            ]
        ],
        [
            [
                28,
                109
            ],
            [
                94,
                111
            ],
            [
                94,
                132
            ],
            [
                27,
                131
            ]
        ],
        [
            [
                120,
                109
            ],
            [
                280,
                109
            ],
            [
                280,
                132
            ],
            [
                120,
                132
            ]
        ],
        [
            [
                288,
                112
            ],
            [
                516,
                112
            ],
            [
                516,
                137
            ],
            [
                288,
                137
            ]
        ],
        [
            [
                26,
                131
            ],
            [
                133,
                133
            ],
            [
                133,
                152
            ],
            [
                25,
                149
            ]
        ],
        [
            [
                175,
                133
            ],
            [
                189,
                133
            ],
            [
                189,
                147
            ],
            [
                175,
                147
            ]
        ],
        [
            [
                222,
                135
            ],
            [
                235,
                135
            ],
            [
                235,
                147
            ],
            [
                222,
                147
            ]
        ],
        [
            [
                268,
                136
            ],
            [
                282,
                136
            ],
            [
                282,
                149
            ],
            [
                268,
                149
            ]
        ],
        [
            [
                288,
                134
            ],
            [
                317,
                136
            ],
            [
                316,
                155
            ],
            [
                287,
                153
            ]
        ],
        [
            [
                376,
                137
            ],
            [
                522,
                138
            ],
            [
                522,
                157
            ],
            [
                376,
                155
            ]
        ],
        [
            [
                25,
                165
            ],
            [
                78,
                165
            ],
            [
                78,
                184
            ],
            [
                25,
                184
            ]
        ],
        [
            [
                98,
                163
            ],
            [
                481,
                165
            ],
            [
                481,
                188
            ],
            [
                98,
                185
            ]
        ],
        [
            [
                24,
                183
            ],
            [
                82,
                183
            ],
            [
                82,
                201
            ],
            [
                24,
                201
            ]
        ],
        [
            [
                23,
                211
            ],
            [
                89,
                211
            ],
            [
                89,
                233
            ],
            [
                23,
                233
            ]
        ],
        [
            [
                100,
                206
            ],
            [
                377,
                211
            ],
            [
                376,
                238
            ],
            [
                100,
                233
            ]
        ],
        [
            [
                19,
                235
            ],
            [
                72,
                235
            ],
            [
                72,
                254
            ],
            [
                19,
                254
            ]
        ],
        [
            [
                87,
                233
            ],
            [
                152,
                235
            ],
            [
                152,
                252
            ],
            [
                86,
                250
            ]
        ],
        [
            [
                86,
                247
            ],
            [
                182,
                249
            ],
            [
                182,
                265
            ],
            [
                86,
                263
            ]
        ],
        [
            [
                336,
                249
            ],
            [
                500,
                252
            ],
            [
                500,
                276
            ],
            [
                336,
                273
            ]
        ],
        [
            [
                85,
                260
            ],
            [
                163,
                263
            ],
            [
                162,
                279
            ],
            [
                85,
                276
            ]
        ],
        [
            [
                192,
                259
            ],
            [
                306,
                261
            ],
            [
                306,
                282
            ],
            [
                192,
                280
            ]
        ],
        [
            [
                86,
                274
            ],
            [
                181,
                276
            ],
            [
                181,
                292
            ],
            [
                85,
                290
            ]
        ],
        [
            [
                336,
                269
            ],
            [
                484,
                272
            ],
            [
                484,
                298
            ],
            [
                336,
                294
            ]
        ],
        [
            [
                20,
                292
            ],
            [
                157,
                294
            ],
            [
                156,
                315
            ],
            [
                20,
                313
            ]
        ],
        [
            [
                19,
                311
            ],
            [
                135,
                313
            ],
            [
                134,
                331
            ],
            [
                19,
                329
            ]
        ],
        [
            [
                185,
                306
            ],
            [
                233,
                306
            ],
            [
                233,
                330
            ],
            [
                185,
                330
            ]
        ],
        [
            [
                232,
                305
            ],
            [
                498,
                310
            ],
            [
                497,
                336
            ],
            [
                232,
                330
            ]
        ],
        [
            [
                20,
                329
            ],
            [
                179,
                331
            ],
            [
                179,
                350
            ],
            [
                20,
                347
            ]
        ],
        [
            [
                208,
                331
            ],
            [
                223,
                331
            ],
            [
                223,
                346
            ],
            [
                208,
                346
            ]
        ],
        [
            [
                469,
                335
            ],
            [
                484,
                335
            ],
            [
                484,
                350
            ],
            [
                469,
                350
            ]
        ],
        [
            [
                17,
                356
            ],
            [
                102,
                356
            ],
            [
                102,
                377
            ],
            [
                17,
                377
            ]
        ],
        [
            [
                111,
                353
            ],
            [
                418,
                358
            ],
            [
                417,
                381
            ],
            [
                110,
                375
            ]
        ],
        [
            [
                444,
                357
            ],
            [
                529,
                357
            ],
            [
                529,
                383
            ],
            [
                444,
                383
            ]
        ],
        [
            [
                14,
                383
            ],
            [
                526,
                391
            ],
            [
                526,
                416
            ],
            [
                13,
                408
            ]
        ],
        [
            [
                709,
                374
            ],
            [
                756,
                377
            ],
            [
                755,
                394
            ],
            [
                708,
                391
            ]
        ],
        [
            [
                12,
                423
            ],
            [
                118,
                424
            ],
            [
                118,
                447
            ],
            [
                11,
                446
            ]
        ],
        [
            [
                142,
                419
            ],
            [
                492,
                426
            ],
            [
                491,
                453
            ],
            [
                142,
                446
            ]
        ],
        [
            [
                712,
                414
            ],
            [
                766,
                418
            ],
            [
                764,
                442
            ],
            [
                711,
                439
            ]
        ],
        [
            [
                507,
                427
            ],
            [
                551,
                429
            ],
            [
                551,
                452
            ],
            [
                506,
                450
            ]
        ],
        [
            [
                575,
                429
            ],
            [
                713,
                433
            ],
            [
                713,
                454
            ],
            [
                574,
                450
            ]
        ],
        [
            [
                714,
                434
            ],
            [
                763,
                434
            ],
            [
                763,
                454
            ],
            [
                714,
                454
            ]
        ],
        [
            [
                191,
                446
            ],
            [
                422,
                449
            ],
            [
                422,
                467
            ],
            [
                191,
                464
            ]
        ],
        [
            [
                713,
                448
            ],
            [
                762,
                448
            ],
            [
                762,
                468
            ],
            [
                713,
                468
            ]
        ]
    ],
    "text_det_params": {
        "limit_side_len": 736,
        "limit_type": "min",
        "thresh": 0.3,
        "max_side_limit": 4000,
        "box_thresh": 0.6,
        "unclip_ratio": 1.5
    },
    "text_type": "general",
    "textline_orientation_angles": [
        -1,
        -1,
        -1,
        -1,
        -1,
        -1,
        -1,
        -1,
        -1,
        -1,
        -1,
        -1,
        -1,
        -1,
        -1,
        -1,
        -1,
        -1,
        -1,
        -1,
        -1,
        -1,
        -1,
        -1,
        -1,
        -1,
        -1,
        -1,
        -1,
        -1,
        -1,
        -1,
        -1,
        -1,
        -1,
        -1,
        -1,
        -1,
        -1,
        -1,
        -1,
        -1,
        -1,
        -1,
        -1,
        -1,
        -1,
        -1,
        -1,
        -1,
        -1,
        -1
    ],
    "text_rec_score_thresh": 0.0,
    "rec_texts": [
        "日本国政府",
        "在留力ード",
        "番号",
        "GOVERNUENT OF JADAN",
        "RESIDENCB CARD",
        "VD",
        "氏名",
        "方雅",
        "NANE",
        "Fang Ya",
        "生年月日",
        "2001年9月10日",
        "生别女F.国籍·地城中国",
        "DATE OF BIRTH",
        "Y",
        "M",
        "D",
        "SEX",
        "NATIONALITY/REGION",
        "住居地",
        "山梨県豊島区10丁目17-20福鉄夕ワ-2798号室",
        "ADDRESS",
        "在留资格",
        "技術·人文知識·国際業務",
        "STATUS",
        "Engineer/",
        "Specialist in",
        "在留資格に基く",
        "Humanities",
        "就労制限の有無",
        "Int IServices",
        "就労活動のみ可",
        "在留期間（满了日）",
        "PERIOD OF STAY",
        "5年",
        "（2026年92日16日）",
        "（DATE OF EXPIRATION)",
        "Y",
        "D",
        "許可の種頼",
        "在留期間更新許可（東京出入国在留管理局長）",
        "MOJ",
        "許可年月日2021年03月16日交付年月日2021年03月16日",
        "MOJ",
        "二のカードは",
        "2026年03月16日まで有效",
        "出人的理",
        "です",
        "出入国在智管理内長富",
        "盗登理员",
        "PERIOD OF VALIDITY OF THIS CARD",
        "医营之面"
    ],
    "rec_scores": [
        0.9975717663764954,
        0.8615433573722839,
        0.990861177444458,
        0.8219961524009705,
        0.9089049100875854,
        0.23200377821922302,
        0.9933434724807739,
        0.9980016946792603,
        0.8784657716751099,
        0.9348470568656921,
        0.9969174861907959,
        0.9992250204086304,
        0.8808745741844177,
        0.9337528944015503,
        0.9766554832458496,
        0.5597821474075317,
        0.93177330493927,
        0.9600443840026855,
        0.9915472865104675,
        0.9310822486877441,
        0.9311082363128662,
        0.9982214570045471,
        0.9670577049255371,
        0.9279572367668152,
        0.9931375980377197,
        0.9308508634567261,
        0.9739049673080444,
        0.9055148959159851,
        0.978206992149353,
        0.9645817875862122,
        0.8625850677490234,
        0.9547141790390015,
        0.9304586052894592,
        0.9392721056938171,
        0.9985440969467163,
        0.9738096594810486,
        0.9098113775253296,
        0.9236844778060913,
        0.9836634397506714,
        0.8116862177848816,
        0.9076008796691895,
        0.9152461886405945,
        0.9951969981193542,
        0.7869879603385925,
        0.8280315399169922,
        0.9506089687347412,
        0.6039155125617981,
        0.9845436811447144,
        0.7679856419563293,
        0.13121899962425232,
        0.9650083184242249,
        0.20054224133491516
    ],
    "rec_polys": [
        [
            [
                32,
                15
            ],
            [
                155,
                15
            ],
            [
                155,
                39
            ],
            [
                32,
                39
            ]
        ],
        [
            [
                304,
                14
            ],
            [
                462,
                13
            ],
            [
                462,
                45
            ],
            [
                304,
                46
            ]
        ],
        [
            [
                541,
                24
            ],
            [
                584,
                24
            ],
            [
                584,
                53
            ],
            [
                541,
                53
            ]
        ],
        [
            [
                31,
                37
            ],
            [
                183,
                37
            ],
            [
                183,
                57
            ],
            [
                31,
                57
            ]
        ],
        [
            [
                319,
                41
            ],
            [
                438,
                41
            ],
            [
                438,
                59
            ],
            [
                319,
                59
            ]
        ],
        [
            [
                563,
                46
            ],
            [
                577,
                46
            ],
            [
                577,
                55
            ],
            [
                563,
                55
            ]
        ],
        [
            [
                31,
                59
            ],
            [
                80,
                59
            ],
            [
                80,
                81
            ],
            [
                31,
                81
            ]
        ],
        [
            [
                75,
                59
            ],
            [
                127,
                59
            ],
            [
                127,
                87
            ],
            [
                75,
                87
            ]
        ],
        [
            [
                29,
                84
            ],
            [
                66,
                84
            ],
            [
                66,
                104
            ],
            [
                29,
                104
            ]
        ],
        [
            [
                77,
                83
            ],
            [
                159,
                83
            ],
            [
                159,
                110
            ],
            [
                77,
                110
            ]
        ],
        [
            [
                28,
                109
            ],
            [
                94,
                111
            ],
            [
                94,
                132
            ],
            [
                27,
                131
            ]
        ],
        [
            [
                120,
                109
            ],
            [
                280,
                109
            ],
            [
                280,
                132
            ],
            [
                120,
                132
            ]
        ],
        [
            [
                288,
                112
            ],
            [
                516,
                112
            ],
            [
                516,
                137
            ],
            [
                288,
                137
            ]
        ],
        [
            [
                26,
                131
            ],
            [
                133,
                133
            ],
            [
                133,
                152
            ],
            [
                25,
                149
            ]
        ],
        [
            [
                175,
                133
            ],
            [
                189,
                133
            ],
            [
                189,
                147
            ],
            [
                175,
                147
            ]
        ],
        [
            [
                222,
                135
            ],
            [
                235,
                135
            ],
            [
                235,
                147
            ],
            [
                222,
                147
            ]
        ],
        [
            [
                268,
                136
            ],
            [
                282,
                136
            ],
            [
                282,
                149
            ],
            [
                268,
                149
            ]
        ],
        [
            [
                288,
                134
            ],
            [
                317,
                136
            ],
            [
                316,
                155
            ],
            [
                287,
                153
            ]
        ],
        [
            [
                376,
                137
            ],
            [
                522,
                138
            ],
            [
                522,
                157
            ],
            [
                376,
                155
            ]
        ],
        [
            [
                25,
                165
            ],
            [
                78,
                165
            ],
            [
                78,
                184
            ],
            [
                25,
                184
            ]
        ],
        [
            [
                98,
                163
            ],
            [
                481,
                165
            ],
            [
                481,
                188
            ],
            [
                98,
                185
            ]
        ],
        [
            [
                24,
                183
            ],
            [
                82,
                183
            ],
            [
                82,
                201
            ],
            [
                24,
                201
            ]
        ],
        [
            [
                23,
                211
            ],
            [
                89,
                211
            ],
            [
                89,
                233
            ],
            [
                23,
                233
            ]
        ],
        [
            [
                100,
                206
            ],
            [
                377,
                211
            ],
            [
                376,
                238
            ],
            [
                100,
                233
            ]
        ],
        [
            [
                19,
                235
            ],
            [
                72,
                235
            ],
            [
                72,
                254
            ],
            [
                19,
                254
            ]
        ],
        [
            [
                87,
                233
            ],
            [
                152,
                235
            ],
            [
                152,
                252
            ],
            [
                86,
                250
            ]
        ],
        [
            [
                86,
                247
            ],
            [
                182,
                249
            ],
            [
                182,
                265
            ],
            [
                86,
                263
            ]
        ],
        [
            [
                336,
                249
            ],
            [
                500,
                252
            ],
            [
                500,
                276
            ],
            [
                336,
                273
            ]
        ],
        [
            [
                85,
                260
            ],
            [
                163,
                263
            ],
            [
                162,
                279
            ],
            [
                85,
                276
            ]
        ],
        [
            [
                192,
                259
            ],
            [
                306,
                261
            ],
            [
                306,
                282
            ],
            [
                192,
                280
            ]
        ],
        [
            [
                86,
                274
            ],
            [
                181,
                276
            ],
            [
                181,
                292
            ],
            [
                85,
                290
            ]
        ],
        [
            [
                336,
                269
            ],
            [
                484,
                272
            ],
            [
                484,
                298
            ],
            [
                336,
                294
            ]
        ],
        [
            [
                20,
                292
            ],
            [
                157,
                294
            ],
            [
                156,
                315
            ],
            [
                20,
                313
            ]
        ],
        [
            [
                19,
                311
            ],
            [
                135,
                313
            ],
            [
                134,
                331
            ],
            [
                19,
                329
            ]
        ],
        [
            [
                185,
                306
            ],
            [
                233,
                306
            ],
            [
                233,
                330
            ],
            [
                185,
                330
            ]
        ],
        [
            [
                232,
                305
            ],
            [
                498,
                310
            ],
            [
                497,
                336
            ],
            [
                232,
                330
            ]
        ],
        [
            [
                20,
                329
            ],
            [
                179,
                331
            ],
            [
                179,
                350
            ],
            [
                20,
                347
            ]
        ],
        [
            [
                208,
                331
            ],
            [
                223,
                331
            ],
            [
                223,
                346
            ],
            [
                208,
                346
            ]
        ],
        [
            [
                469,
                335
            ],
            [
                484,
                335
            ],
            [
                484,
                350
            ],
            [
                469,
                350
            ]
        ],
        [
            [
                17,
                356
            ],
            [
                102,
                356
            ],
            [
                102,
                377
            ],
            [
                17,
                377
            ]
        ],
        [
            [
                111,
                353
            ],
            [
                418,
                358
            ],
            [
                417,
                381
            ],
            [
                110,
                375
            ]
        ],
        [
            [
                444,
                357
            ],
            [
                529,
                357
            ],
            [
                529,
                383
            ],
            [
                444,
                383
            ]
        ],
        [
            [
                14,
                383
            ],
            [
                526,
                391
            ],
            [
                526,
                416
            ],
            [
                13,
                408
            ]
        ],
        [
            [
                709,
                374
            ],
            [
                756,
                377
            ],
            [
                755,
                394
            ],
            [
                708,
                391
            ]
        ],
        [
            [
                12,
                423
            ],
            [
                118,
                424
            ],
            [
                118,
                447
            ],
            [
                11,
                446
            ]
        ],
        [
            [
                142,
                419
            ],
            [
                492,
                426
            ],
            [
                491,
                453
            ],
            [
                142,
                446
            ]
        ],
        [
            [
                712,
                414
            ],
            [
                766,
                418
            ],
            [
                764,
                442
            ],
            [
                711,
                439
            ]
        ],
        [
            [
                507,
                427
            ],
            [
                551,
                429
            ],
            [
                551,
                452
            ],
            [
                506,
                450
            ]
        ],
        [
            [
                575,
                429
            ],
            [
                713,
                433
            ],
            [
                713,
                454
            ],
            [
                574,
                450
            ]
        ],
        [
            [
                714,
                434
            ],
            [
                763,
                434
            ],
            [
                763,
                454
            ],
            [
                714,
                454
            ]
        ],
        [
            [
                191,
                446
            ],
            [
                422,
                449
            ],
            [
                422,
                467
            ],
            [
                191,
                464
            ]
        ],
        [
            [
                713,
                448
            ],
            [
                762,
                448
            ],
            [
                762,
                468
            ],
            [
                713,
                468
            ]
        ]
    ],
    "rec_boxes": [
        [
            32,
            15,
            155,
            39
        ],
        [
            304,
            13,
            462,
            46
        ],
        [
            541,
            24,
            584,
            53
        ],
        [
            31,
            37,
            183,
            57
        ],
        [
            319,
            41,
            438,
            59
        ],
        [
            563,
            46,
            577,
            55
        ],
        [
            31,
            59,
            80,
            81
        ],
        [
            75,
            59,
            127,
            87
        ],
        [
            29,
            84,
            66,
            104
        ],
        [
            77,
            83,
            159,
            110
        ],
        [
            27,
            109,
            94,
            132
        ],
        [
            120,
            109,
            280,
            132
        ],
        [
            288,
            112,
            516,
            137
        ],
        [
            25,
            131,
            133,
            152
        ],
        [
            175,
            133,
            189,
            147
        ],
        [
            222,
            135,
            235,
            147
        ],
        [
            268,
            136,
            282,
            149
        ],
        [
            287,
            134,
            317,
            155
        ],
        [
            376,
            137,
            522,
            157
        ],
        [
            25,
            165,
            78,
            184
        ],
        [
            98,
            163,
            481,
            188
        ],
        [
            24,
            183,
            82,
            201
        ],
        [
            23,
            211,
            89,
            233
        ],
        [
            100,
            206,
            377,
            238
        ],
        [
            19,
            235,
            72,
            254
        ],
        [
            86,
            233,
            152,
            252
        ],
        [
            86,
            247,
            182,
            265
        ],
        [
            336,
            249,
            500,
            276
        ],
        [
            85,
            260,
            163,
            279
        ],
        [
            192,
            259,
            306,
            282
        ],
        [
            85,
            274,
            181,
            292
        ],
        [
            336,
            269,
            484,
            298
        ],
        [
            20,
            292,
            157,
            315
        ],
        [
            19,
            311,
            135,
            331
        ],
        [
            185,
            306,
            233,
            330
        ],
        [
            232,
            305,
            498,
            336
        ],
        [
            20,
            329,
            179,
            350
        ],
        [
            208,
            331,
            223,
            346
        ],
        [
            469,
            335,
            484,
            350
        ],
        [
            17,
            356,
            102,
            377
        ],
        [
            110,
            353,
            418,
            381
        ],
        [
            444,
            357,
            529,
            383
        ],
        [
            13,
            383,
            526,
            416
        ],
        [
            708,
            374,
            756,
            394
        ],
        [
            11,
            423,
            118,
            447
        ],
        [
            142,
            419,
            492,
            453
        ],
        [
            711,
            414,
            766,
            442
        ],
        [
            506,
            427,
            551,
            452
        ],
        [
            574,
            429,
            713,
            454
        ],
        [
            714,
            434,
            763,
            454
        ],
        [
            191,
            446,
            422,
            467
        ],
        [
            713,
            448,
            762,
            468
        ]
    ]
}